pytoy/__init__.py
pytoy/cli.py
pytoy/cli_file.py
pytoy/common.py
pytoy/nginx.py
pytoy-0.0.4.dist-info/METADATA
pytoy-0.0.4.dist-info/WHEEL
pytoy-0.0.4.dist-info/entry_points.txt
pytoy-0.0.4.dist-info/licenses/LICENSE
pytoy-0.0.4.dist-info/RECORD
